{
  "users": [
    {
      "name": "Ruymán",
      "lastName": "Padrón",
      "secondLastName": "Catsañeda",
      "gender": "Masculino",
      "birthdate": "1997-09-01T23:00:00.000Z",
      "idNumber": "44558825J",
      "address": {
        "street": "San Cipriano",
        "number": "5",
        "door": "1º E",
        "postalCode": "28018",
        "city": "Madrid"
      },
      "NHC": "87563212",
      "insurance": [
        {
          "cardNumber": "12345679",
          "name": "Mi Seguro",
          "type": "salud"
        },
        {
          "cardNumber": "987654321",
          "name": "Mi Seguro2",
          "type": "dental"
        }
      ],
      "id": 1
    },
    {
      "name": "Silvia",
      "lastName": "Sánchez",
      "secondLastName": "Sánchez",
      "gender": "Femenino",
      "birthdate": "1998-11-27T00:00:00.000Z",
      "idNumber": "77889966R",
      "address": {
        "street": "",
        "number": "",
        "door": "",
        "postalCode": "",
        "city": ""
      },
      "NHC": "77663215",
      "insurance": [],
      "id": 3
    },
    {
      "name": "Daniel",
      "lastName": "Castañeda",
      "secondLastName": "Campos",
      "gender": "",
      "birthdate": "",
      "idNumber": "",
      "address": {
        "street": "",
        "number": "",
        "door": "",
        "postalCode": "",
        "city": ""
      },
      "NHC": "56214578",
      "insurance": [
        {
          "cardNumber": "132564897",
          "name": "Mapfre",
          "type": "familiar"
        }
      ],
      "id": 5
    },
    {
      "name": "Santiago",
      "lastName": "González",
      "secondLastName": "González",
      "gender": "Masculino",
      "birthdate": "1925-11-12T01:00:00.000Z",
      "idNumber": "75521256T",
      "address": {
        "street": "San Pedro",
        "number": "5",
        "door": "",
        "postalCode": "38916",
        "city": "El Mocanal"
      },
      "NHC": "97856421",
      "insurance": [
        {
          "cardNumber": "789456132",
          "name": "Mapfre",
          "type": "salud"
        },
        {
          "cardNumber": "321654987",
          "name": "Mutua",
          "type": "familiar"
        },
        {
          "cardNumber": "071456987",
          "name": "Mutua",
          "type": "dental"
        }
      ],
      "id": 7
    },
    {
      "name": "Andrea",
      "lastName": " Heras",
      "secondLastName": "Puerta",
      "gender": "Femenino",
      "birthdate": "",
      "idNumber": "",
      "address": {
        "street": "",
        "number": "",
        "door": "",
        "postalCode": "",
        "city": ""
      },
      "NHC": "99856321",
      "insurance": [],
      "id": 8
    },
    {
      "name": "Yolanda",
      "lastName": "Campos",
      "secondLastName": "",
      "gender": "Femenino",
      "birthdate": "",
      "idNumber": "",
      "address": {
        "street": "",
        "number": "",
        "door": "",
        "postalCode": "",
        "city": ""
      },
      "NHC": "25654178",
      "insurance": [],
      "id": 9
    },
    {
      "name": "Manuel",
      "lastName": "Alonso",
      "secondLastName": "",
      "gender": "",
      "birthdate": "",
      "idNumber": "",
      "address": {
        "street": "",
        "number": "",
        "door": "",
        "postalCode": "",
        "city": ""
      },
      "medicalBoardNumber": "55662385",
      "professionalType": "Médico",
      "id": 10
    },
    {
      "name": "Pedro",
      "lastName": "Sánchez",
      "secondLastName": "Castejón",
      "gender": "Masculino",
      "birthdate": "1954-06-10T00:00:00.000Z",
      "idNumber": "78541232T",
      "address": {
        "street": "Alcalá",
        "number": "5",
        "door": "4º E",
        "postalCode": "28018",
        "city": "Madrid"
      },
      "medicalBoardNumber": "78563212",
      "professionalType": "Administrativo",
      "id": 11
    },
    {
      "name": "Pablo",
      "lastName": "Iglesias",
      "secondLastName": "Iglesias",
      "gender": "Masculino",
      "birthdate": "1958-03-06T00:00:00.000Z",
      "idNumber": "78563214P",
      "address": {
        "street": "Pº Castellana",
        "number": "1",
        "door": "5",
        "postalCode": "28018",
        "city": "Madrid"
      },
      "medicalBoardNumber": "78951416",
      "professionalType": "Enfermero",
      "id": 12
    },
    {
      "name": "Pablo",
      "lastName": "Casado",
      "secondLastName": "Blanco",
      "gender": "Masculino",
      "birthdate": "1954-07-10T00:00:00.000Z",
      "idNumber": "45632546B",
      "address": {
        "street": "Génova",
        "number": "1",
        "door": "A",
        "postalCode": "28036",
        "city": "Madrid"
      },
      "medicalBoardNumber": "54230156",
      "professionalType": "Médico",
      "id": 13
    }
  ]
}